<annotation>
	<folder>data_images</folder>
	<filename>21.jpg</filename>
	<path>C:\Users\DELL\OneDrive\Desktop\yolo\data_preparation\data_images\21.jpg</path>
	<source>
		<database>Unknown</database>
	</source>
	<size>
		<width>612</width>
		<height>242</height>
		<depth>3</depth>
	</size>
	<segmented>0</segmented>
	<object>
		<name>boulder</name>
		<pose>Unspecified</pose>
		<truncated>0</truncated>
		<difficult>0</difficult>
		<bndbox>
			<xmin>360</xmin>
			<ymin>128</ymin>
			<xmax>394</xmax>
			<ymax>157</ymax>
		</bndbox>
	</object>
	<object>
		<name>boulder</name>
		<pose>Unspecified</pose>
		<truncated>0</truncated>
		<difficult>0</difficult>
		<bndbox>
			<xmin>379</xmin>
			<ymin>181</ymin>
			<xmax>427</xmax>
			<ymax>210</ymax>
		</bndbox>
	</object>
</annotation>
